causalinference/__init__.py
causalinference/_version.py
causalinference/core/__init__.py
causalinference/core/async_processing.py
causalinference/core/caching.py
causalinference/core/causal_discovery.py
causalinference/core/causal_llm_core.py
causalinference/core/counterfactual_engine.py
causalinference/core/dag_parser.py
causalinference/core/data_processing.py
causalinference/core/do_operator.py
causalinference/core/enhanced_causal_discovery.py
causalinference/core/exceptions.py
causalinference/core/factory.py
causalinference/core/interfaces.py
causalinference/core/lazy_evaluation.py
causalinference/core/llm_client.py
causalinference/core/optimized_algorithms.py
causalinference/core/prompt_templates.py
causalinference/core/statistical_inference.py
causalinference/core/statistical_methods.py
causalinference/core/validation.py
causalinference/core/utils/__init__.py
causalinference/core/utils/data_utils.py
causalinference/core/utils/logging.py
causalinference/core/utils/validation.py
statistical_causal_inference-4.4.0.dist-info/licenses/LICENSE
statistical_causal_inference-4.4.0.dist-info/METADATA
statistical_causal_inference-4.4.0.dist-info/WHEEL
statistical_causal_inference-4.4.0.dist-info/top_level.txt
statistical_causal_inference-4.4.0.dist-info/RECORD
