Metadata-Version: 2.4
Name: statistical-causal-inference
Version: 4.4.0
Summary: Production-ready causal attribution and inference API with comprehensive monitoring, testing, and LLM integration
Home-page: https://github.com/rdmurugan/statistical-causal-inference
Author: CausalMMA Team
Author-email: durai@infinidatum.net
Project-URL: Bug Tracker, https://github.com/rdmurugan/statistical-causal-inference/issues
Project-URL: Documentation, https://github.com/rdmurugan/statistical-causal-inference
Project-URL: Source Code, https://github.com/rdmurugan/statistical-causal-inference
Keywords: causal-inference,machine-learning,statistics,llm,artificial-intelligence,performance,scalability,async,vectorization
Classifier: Development Status :: 4 - Beta
Classifier: Intended Audience :: Developers
Classifier: Intended Audience :: Science/Research
Classifier: License :: Other/Proprietary License
Classifier: Operating System :: OS Independent
Classifier: Programming Language :: Python :: 3
Classifier: Programming Language :: Python :: 3.9
Classifier: Programming Language :: Python :: 3.10
Classifier: Programming Language :: Python :: 3.11
Classifier: Programming Language :: Python :: 3.12
Classifier: Programming Language :: Python :: 3.13
Classifier: Topic :: Scientific/Engineering :: Artificial Intelligence
Classifier: Topic :: Scientific/Engineering :: Mathematics
Classifier: Topic :: Software Development :: Libraries :: Python Modules
Requires-Python: >=3.9
License-File: LICENSE
Requires-Dist: numpy>=1.21.0
Requires-Dist: pandas>=1.3.0
Requires-Dist: scikit-learn>=1.0.0
Requires-Dist: networkx>=2.6.0
Requires-Dist: scipy>=1.7.0
Requires-Dist: matplotlib>=3.3.0
Requires-Dist: plotly>=5.0.0
Requires-Dist: openai>=1.0.0
Requires-Dist: numba>=0.56.0
Requires-Dist: dask>=2022.1.0
Requires-Dist: psutil>=5.8.0
Requires-Dist: pyyaml>=6.0.0
Requires-Dist: aiofiles>=23.0.0
Requires-Dist: pyarrow>=10.0.0
Provides-Extra: dev
Requires-Dist: pytest>=7.0.0; extra == "dev"
Requires-Dist: pytest-asyncio>=0.21.0; extra == "dev"
Requires-Dist: pytest-cov>=4.0.0; extra == "dev"
Requires-Dist: black>=22.0.0; extra == "dev"
Requires-Dist: flake8>=4.0.0; extra == "dev"
Requires-Dist: mypy>=1.0.0; extra == "dev"
Requires-Dist: pre-commit>=3.0.0; extra == "dev"
Provides-Extra: full
Requires-Dist: langchain>=0.0.200; extra == "full"
Requires-Dist: llama-index>=0.7.0; extra == "full"
Requires-Dist: transformers>=4.20.0; extra == "full"
Requires-Dist: torch>=1.11.0; extra == "full"
Requires-Dist: streamlit>=1.25.0; extra == "full"
Requires-Dist: anthropic>=0.7.0; extra == "full"
Dynamic: author
Dynamic: author-email
Dynamic: classifier
Dynamic: description
Dynamic: description-content-type
Dynamic: home-page
Dynamic: keywords
Dynamic: license-file
Dynamic: project-url
Dynamic: provides-extra
Dynamic: requires-dist
Dynamic: requires-python
Dynamic: summary
